{
  "slug": "hifu-treatment",
  "title": "HIFU Treatment in Pune",
  "category": "68e307eca806d2e658b710c0",
  "updatedAt": "2025-10-05T22:27:11.130Z",
  "createdAt": "2025-10-05T22:27:11.130Z",
  "sections": [
    {
      "id": "68e2f0bfe7637d71e1736215",
      "title": {
        "root": {
          "children": [
            {
              "children": [
                {
                  "detail": 0,
                  "format": 0,
                  "mode": "normal",
                  "style": "",
                  "text": "HIFU Treatment in Pune - Non-Surgical Facelift with The Skin Firm",
                  "type": "text",
                  "version": 1
                }
              ],
              "direction": null,
              "format": "start",
              "indent": 0,
              "type": "heading",
              "version": 1,
              "tag": "h1"
            }
          ],
          "direction": null,
          "format": "",
          "indent": 0,
          "type": "root",
          "version": 1
        }
      },
      "description": {
        "root": {
          "children": [
            {
              "children": [
                {
                  "detail": 0,
                  "format": 0,
                  "mode": "normal",
                  "style": "",
                  "text": "Tighten, lift, and rejuvenate your skin naturally with advanced High-Intensity Focused Ultrasound (HIFU) treatment at The Skin Firm. ✨ Restore firmness without surgery or downtime.",
                  "type": "text",
                  "version": 1
                }
              ],
              "direction": null,
              "format": "start",
              "indent": 0,
              "type": "heading",
              "version": 1,
              "tag": "h4"
            }
          ],
          "direction": null,
          "format": "",
          "indent": 0,
          "type": "root",
          "version": 1
        }
      },
      "blockType": "hero"
    },
    {
      "id": "68e2f0bffea9fa4eab6c2691",
      "title": {
        "root": {
          "children": [
            {
              "children": [
                {
                  "detail": 0,
                  "format": 0,
                  "mode": "normal",
                  "style": "",
                  "text": "What Is HIFU?",
                  "type": "text",
                  "version": 1
                }
              ],
              "direction": null,
              "format": "center",
              "indent": 0,
              "type": "heading",
              "version": 1,
              "tag": "h2"
            }
          ],
          "direction": null,
          "format": "",
          "indent": 0,
          "type": "root",
          "version": 1
        }
      },
      "description": {
        "root": {
          "children": [
            {
              "children": [
                {
                  "detail": 0,
                  "format": 0,
                  "mode": "normal",
                  "style": "",
                  "text": "HIFU, or High-Intensity Focused Ultrasound, is a revolutionary non-invasive anti-ageing treatment that uses ultrasound energy to stimulate collagen production in the deeper layers of the skin.",
                  "type": "text",
                  "version": 1
                }
              ],
              "direction": null,
              "format": "center",
              "indent": 0,
              "type": "paragraph",
              "version": 1
            },
            {
              "children": [
                {
                  "detail": 0,
                  "format": 0,
                  "mode": "normal",
                  "style": "",
                  "text": "Unlike facials or creams that work only on the surface, HIFU penetrates below the skin to lift, tighten, and improve elasticity all without surgery, needles, or significant downtime.",
                  "type": "text",
                  "version": 1
                }
              ],
              "direction": null,
              "format": "center",
              "indent": 0,
              "type": "paragraph",
              "version": 1
            },
            {
              "children": [
                {
                  "detail": 0,
                  "format": 0,
                  "mode": "normal",
                  "style": "",
                  "text": "It’s often called a “lunchtime facelift” because it delivers visible lifting and tightening with minimal discomfort and quick recovery. At The Skin Firm, we customise every HIFU session to target sagging, fine lines, double chin, or jawline definition, giving you a refreshed and youthful look.",
                  "type": "text",
                  "version": 1
                }
              ],
              "direction": null,
              "format": "center",
              "indent": 0,
              "type": "paragraph",
              "version": 1
            }
          ],
          "direction": null,
          "format": "",
          "indent": 0,
          "type": "root",
          "version": 1
        }
      },
      "blockType": "info"
    },
    {
      "id": "68e2f0bf9578c6ea6ab938c7",
      "title": {
        "root": {
          "children": [
            {
              "children": [
                {
                  "detail": 0,
                  "format": 0,
                  "mode": "normal",
                  "style": "",
                  "text": "Signs & Concerns HIFU Can Treat",
                  "type": "text",
                  "version": 1
                }
              ],
              "direction": null,
              "format": "center",
              "indent": 0,
              "type": "heading",
              "version": 1,
              "tag": "h2"
            }
          ],
          "direction": null,
          "format": "",
          "indent": 0,
          "type": "root",
          "version": 1
        }
      },
      "items": [
        {
          "id": "68e2f0bff14f266e389070e1",
          "content": {
            "root": {
              "children": [
                {
                  "children": [
                    {
                      "detail": 0,
                      "format": 0,
                      "mode": "normal",
                      "style": "",
                      "text": "Sagging skin on face, neck, or jawline",
                      "type": "text",
                      "version": 1
                    }
                  ],
                  "direction": null,
                  "format": "left",
                  "indent": 0,
                  "type": "paragraph",
                  "version": 1
                }
              ],
              "direction": null,
              "format": "",
              "indent": 0,
              "type": "root",
              "version": 1
            }
          }
        },
        {
          "id": "68e2f0bf662ed6256c823691",
          "content": {
            "root": {
              "children": [
                {
                  "children": [
                    {
                      "detail": 0,
                      "format": 0,
                      "mode": "normal",
                      "style": "",
                      "text": "Drooping eyebrows or eyelids",
                      "type": "text",
                      "version": 1
                    }
                  ],
                  "direction": null,
                  "format": "left",
                  "indent": 0,
                  "type": "paragraph",
                  "version": 1
                }
              ],
              "direction": null,
              "format": "",
              "indent": 0,
              "type": "root",
              "version": 1
            }
          }
        },
        {
          "id": "68e2f0bfb5e0044e85ee77d7",
          "content": {
            "root": {
              "children": [
                {
                  "children": [
                    {
                      "detail": 0,
                      "format": 0,
                      "mode": "normal",
                      "style": "",
                      "text": "Double chin or undefined jawline",
                      "type": "text",
                      "version": 1
                    }
                  ],
                  "direction": null,
                  "format": "left",
                  "indent": 0,
                  "type": "paragraph",
                  "version": 1
                }
              ],
              "direction": null,
              "format": "",
              "indent": 0,
              "type": "root",
              "version": 1
            }
          }
        },
        {
          "id": "68e2f0bf44cc2e7f9a133f38",
          "content": {
            "root": {
              "children": [
                {
                  "children": [
                    {
                      "detail": 0,
                      "format": 0,
                      "mode": "normal",
                      "style": "",
                      "text": "Fine lines and wrinkles",
                      "type": "text",
                      "version": 1
                    }
                  ],
                  "direction": null,
                  "format": "left",
                  "indent": 0,
                  "type": "paragraph",
                  "version": 1
                }
              ],
              "direction": null,
              "format": "",
              "indent": 0,
              "type": "root",
              "version": 1
            }
          }
        },
        {
          "id": "68e2f0bf9ad56eafce15d984",
          "content": {
            "root": {
              "children": [
                {
                  "children": [
                    {
                      "detail": 0,
                      "format": 0,
                      "mode": "normal",
                      "style": "",
                      "text": "Mild tmoderate skin laxity",
                      "type": "text",
                      "version": 1
                    }
                  ],
                  "direction": null,
                  "format": "left",
                  "indent": 0,
                  "type": "paragraph",
                  "version": 1
                }
              ],
              "direction": null,
              "format": "",
              "indent": 0,
              "type": "root",
              "version": 1
            }
          }
        },
        {
          "id": "68e2f0bf73511d88a5ef4ea9",
          "content": {
            "root": {
              "children": [
                {
                  "children": [
                    {
                      "detail": 0,
                      "format": 0,
                      "mode": "normal",
                      "style": "",
                      "text": "Uneven skin tone and texture",
                      "type": "text",
                      "version": 1
                    }
                  ],
                  "direction": null,
                  "format": "left",
                  "indent": 0,
                  "type": "paragraph",
                  "version": 1
                }
              ],
              "direction": null,
              "format": "",
              "indent": 0,
              "type": "root",
              "version": 1
            }
          }
        },
        {
          "id": "68e2f0bf8dffb1be507e3444",
          "content": {
            "root": {
              "children": [
                {
                  "children": [
                    {
                      "detail": 0,
                      "format": 0,
                      "mode": "normal",
                      "style": "",
                      "text": "Early signs of ageing (30s-50s)",
                      "type": "text",
                      "version": 1
                    }
                  ],
                  "direction": null,
                  "format": "left",
                  "indent": 0,
                  "type": "paragraph",
                  "version": 1
                }
              ],
              "direction": null,
              "format": "",
              "indent": 0,
              "type": "root",
              "version": 1
            }
          }
        }
      ],
      "blockType": "bullet-points"
    },
    {
      "id": "68e2f0bf2e67116609be0ecc",
      "title": {
        "root": {
          "children": [
            {
              "children": [
                {
                  "detail": 0,
                  "format": 0,
                  "mode": "normal",
                  "style": "",
                  "text": "Why Choose HIFU at The Skin Firm?",
                  "type": "text",
                  "version": 1
                }
              ],
              "direction": null,
              "format": "start",
              "indent": 0,
              "type": "heading",
              "version": 1,
              "tag": "h2"
            }
          ],
          "direction": null,
          "format": "",
          "indent": 0,
          "type": "root",
          "version": 1
        }
      },
      "description": {
        "root": {
          "children": [
            {
              "children": [
                {
                  "detail": 0,
                  "format": 0,
                  "mode": "normal",
                  "style": "",
                  "text": "As we age, collagen levels naturally decline, leading to sagging and wrinkles. If you’re not ready for surgery but want visible lifting and tightening, HIFU is an excellent choice.",
                  "type": "text",
                  "version": 1
                }
              ],
              "direction": null,
              "format": "start",
              "indent": 0,
              "type": "paragraph",
              "version": 1
            },
            {
              "children": [
                {
                  "detail": 0,
                  "format": 0,
                  "mode": "normal",
                  "style": "",
                  "text": "At The Skin Firm, treatments are supervised by Skin Specialist Dr. Karishma Singh, ensuring safety, comfort, and natural-looking results. With medical-grade HIFU technology and personalised treatment mapping, we help you achieve firmer, more youthful skin without going under the knife.",
                  "type": "text",
                  "version": 1
                }
              ],
              "direction": null,
              "format": "start",
              "indent": 0,
              "type": "paragraph",
              "version": 1
            },
            {
              "children": [],
              "direction": null,
              "format": "start",
              "indent": 0,
              "type": "paragraph",
              "version": 1
            }
          ],
          "direction": null,
          "format": "",
          "indent": 0,
          "type": "root",
          "version": 1
        }
      },
      "blockType": "about",
      "image": "68e25156a21844875a4b767a"
    },
    {
      "id": "68e2f0bf4283fee7a2bd1489",
      "title": {
        "root": {
          "children": [
            {
              "children": [
                {
                  "detail": 0,
                  "format": 0,
                  "mode": "normal",
                  "style": "",
                  "text": "How Our HIFU Treatment Works",
                  "type": "text",
                  "version": 1
                }
              ],
              "direction": null,
              "format": "center",
              "indent": 0,
              "type": "heading",
              "version": 1,
              "tag": "h2"
            }
          ],
          "direction": null,
          "format": "",
          "indent": 0,
          "type": "root",
          "version": 1
        }
      },
      "items": [
        {
          "id": "68e2f0bf35330349535bba57",
          "title": "Consultation & Skin Assessment",
          "description": {
            "root": {
              "children": [
                {
                  "children": [
                    {
                      "detail": 0,
                      "format": 0,
                      "mode": "normal",
                      "style": "",
                      "text": "We evaluate your skin’s laxity, areas of concern, and suitability for HIFU.",
                      "type": "text",
                      "version": 1
                    }
                  ],
                  "direction": null,
                  "format": "",
                  "indent": 0,
                  "type": "paragraph",
                  "version": 1
                }
              ],
              "direction": null,
              "format": "",
              "indent": 0,
              "type": "root",
              "version": 1
            }
          }
        },
        {
          "id": "68e2f0bf742ec4aab53e4230",
          "title": "Cleansing & Marking",
          "description": {
            "root": {
              "children": [
                {
                  "children": [
                    {
                      "detail": 0,
                      "format": 0,
                      "mode": "normal",
                      "style": "",
                      "text": "Skin is cleansed, and treatment areas are mapped for precision.",
                      "type": "text",
                      "version": 1
                    }
                  ],
                  "direction": null,
                  "format": "",
                  "indent": 0,
                  "type": "paragraph",
                  "version": 1
                }
              ],
              "direction": null,
              "format": "",
              "indent": 0,
              "type": "root",
              "version": 1
            }
          }
        },
        {
          "id": "68e2f0bfe3e8d98564f588c0",
          "title": "Ultrasound Energy Delivery",
          "description": {
            "root": {
              "children": [
                {
                  "children": [
                    {
                      "detail": 0,
                      "format": 0,
                      "mode": "normal",
                      "style": "",
                      "text": "Focused ultrasound waves penetrate deep into the skin layers, stimulating collagen and tightening tissue.",
                      "type": "text",
                      "version": 1
                    }
                  ],
                  "direction": null,
                  "format": "",
                  "indent": 0,
                  "type": "paragraph",
                  "version": 1
                }
              ],
              "direction": null,
              "format": "",
              "indent": 0,
              "type": "root",
              "version": 1
            }
          }
        },
        {
          "id": "68e2f0bfa4bc243cf0713d5f",
          "title": "Cooling & Soothing",
          "description": {
            "root": {
              "children": [
                {
                  "children": [
                    {
                      "detail": 0,
                      "format": 0,
                      "mode": "normal",
                      "style": "",
                      "text": "A soothing gel is applied to calm the skin.",
                      "type": "text",
                      "version": 1
                    }
                  ],
                  "direction": null,
                  "format": "",
                  "indent": 0,
                  "type": "paragraph",
                  "version": 1
                }
              ],
              "direction": null,
              "format": "",
              "indent": 0,
              "type": "root",
              "version": 1
            }
          }
        },
        {
          "id": "68e2f0bf210c0a240ddb72a5",
          "title": "Aftercare & Guidance",
          "description": {
            "root": {
              "children": [
                {
                  "children": [
                    {
                      "detail": 0,
                      "format": 0,
                      "mode": "normal",
                      "style": "",
                      "text": "We provide skincare and lifestyle advice to maintain results.",
                      "type": "text",
                      "version": 1
                    }
                  ],
                  "direction": null,
                  "format": "",
                  "indent": 0,
                  "type": "paragraph",
                  "version": 1
                }
              ],
              "direction": null,
              "format": "",
              "indent": 0,
              "type": "root",
              "version": 1
            }
          }
        }
      ],
      "blockType": "process"
    },
    {
      "id": "68e2f0bf3811ffee3ac70669",
      "title": {
        "root": {
          "children": [
            {
              "children": [
                {
                  "detail": 0,
                  "format": 0,
                  "mode": "normal",
                  "style": "",
                  "text": "Benefits of HIFU at The Skin Firm",
                  "type": "text",
                  "version": 1
                }
              ],
              "direction": null,
              "format": "center",
              "indent": 0,
              "type": "heading",
              "version": 1,
              "tag": "h2"
            }
          ],
          "direction": null,
          "format": "",
          "indent": 0,
          "type": "root",
          "version": 1
        }
      },
      "items": [
        {
          "id": "68e2f0bf953385e75f0839aa",
          "content": {
            "root": {
              "children": [
                {
                  "children": [
                    {
                      "detail": 0,
                      "format": 0,
                      "mode": "normal",
                      "style": "",
                      "text": "Natural skin tightening without surgery",
                      "type": "text",
                      "version": 1
                    }
                  ],
                  "direction": null,
                  "format": "",
                  "indent": 0,
                  "type": "paragraph",
                  "version": 1
                }
              ],
              "direction": null,
              "format": "",
              "indent": 0,
              "type": "root",
              "version": 1
            }
          }
        },
        {
          "id": "68e2f0bff2ab6ab3d01e62ed",
          "content": {
            "root": {
              "children": [
                {
                  "children": [
                    {
                      "detail": 0,
                      "format": 0,
                      "mode": "normal",
                      "style": "",
                      "text": "Stimulates collagen and elastin production",
                      "type": "text",
                      "version": 1
                    }
                  ],
                  "direction": null,
                  "format": "",
                  "indent": 0,
                  "type": "paragraph",
                  "version": 1
                }
              ],
              "direction": null,
              "format": "",
              "indent": 0,
              "type": "root",
              "version": 1
            }
          }
        },
        {
          "id": "68e2f0bf6937877df78e267c",
          "content": {
            "root": {
              "children": [
                {
                  "children": [
                    {
                      "detail": 0,
                      "format": 0,
                      "mode": "normal",
                      "style": "",
                      "text": "Lifts sagging jawline, cheeks, and brows",
                      "type": "text",
                      "version": 1
                    }
                  ],
                  "direction": null,
                  "format": "",
                  "indent": 0,
                  "type": "paragraph",
                  "version": 1
                }
              ],
              "direction": null,
              "format": "",
              "indent": 0,
              "type": "root",
              "version": 1
            }
          }
        },
        {
          "id": "68e2f0bf6ca7f454f788a8ad",
          "content": {
            "root": {
              "children": [
                {
                  "children": [
                    {
                      "detail": 0,
                      "format": 0,
                      "mode": "normal",
                      "style": "",
                      "text": "Improves fine lines and wrinkles",
                      "type": "text",
                      "version": 1
                    }
                  ],
                  "direction": null,
                  "format": "",
                  "indent": 0,
                  "type": "paragraph",
                  "version": 1
                }
              ],
              "direction": null,
              "format": "",
              "indent": 0,
              "type": "root",
              "version": 1
            }
          }
        },
        {
          "id": "68e2f0bf0e4b9c8148e22d9c",
          "content": {
            "root": {
              "children": [
                {
                  "children": [
                    {
                      "detail": 0,
                      "format": 0,
                      "mode": "normal",
                      "style": "",
                      "text": "Defines facial contours and reduces double chin",
                      "type": "text",
                      "version": 1
                    }
                  ],
                  "direction": null,
                  "format": "",
                  "indent": 0,
                  "type": "paragraph",
                  "version": 1
                }
              ],
              "direction": null,
              "format": "",
              "indent": 0,
              "type": "root",
              "version": 1
            }
          }
        },
        {
          "id": "68e2f0bf15f94f388224eda2",
          "content": {
            "root": {
              "children": [
                {
                  "children": [
                    {
                      "detail": 0,
                      "format": 0,
                      "mode": "normal",
                      "style": "",
                      "text": "Long-lasting results (up to 12-18 months)",
                      "type": "text",
                      "version": 1
                    }
                  ],
                  "direction": null,
                  "format": "",
                  "indent": 0,
                  "type": "paragraph",
                  "version": 1
                }
              ],
              "direction": null,
              "format": "",
              "indent": 0,
              "type": "root",
              "version": 1
            }
          }
        },
        {
          "id": "68e2f0bfe6d1a54e629b0dc7",
          "content": {
            "root": {
              "children": [
                {
                  "children": [
                    {
                      "detail": 0,
                      "format": 0,
                      "mode": "normal",
                      "style": "",
                      "text": "Safe, quick, and minimal downtime",
                      "type": "text",
                      "version": 1
                    }
                  ],
                  "direction": null,
                  "format": "",
                  "indent": 0,
                  "type": "paragraph",
                  "version": 1
                }
              ],
              "direction": null,
              "format": "",
              "indent": 0,
              "type": "root",
              "version": 1
            }
          }
        }
      ],
      "blockType": "benifits"
    },
    {
      "id": "68e2f0bf38f585cacffb154c",
      "downtimeTitle": {
        "root": {
          "children": [
            {
              "children": [
                {
                  "detail": 0,
                  "format": 0,
                  "mode": "normal",
                  "style": "",
                  "text": "Post-Care After HIFU",
                  "type": "text",
                  "version": 1
                }
              ],
              "direction": null,
              "format": "center",
              "indent": 0,
              "type": "heading",
              "version": 1,
              "tag": "h2"
            }
          ],
          "direction": null,
          "format": "",
          "indent": 0,
          "type": "root",
          "version": 1
        }
      },
      "downtime": [
        {
          "id": "68e2f0bff5767bf7a5a1a117",
          "content": {
            "root": {
              "children": [
                {
                  "children": [
                    {
                      "detail": 0,
                      "format": 0,
                      "mode": "normal",
                      "style": "",
                      "text": "Redness or Warmth - may last a few hours",
                      "type": "text",
                      "version": 1
                    }
                  ],
                  "direction": null,
                  "format": "",
                  "indent": 0,
                  "type": "paragraph",
                  "version": 1
                }
              ],
              "direction": null,
              "format": "",
              "indent": 0,
              "type": "root",
              "version": 1
            }
          }
        },
        {
          "id": "68e2f0bf50bd5ac4e32f7eed",
          "content": {
            "root": {
              "children": [
                {
                  "children": [
                    {
                      "detail": 0,
                      "format": 0,
                      "mode": "normal",
                      "style": "",
                      "text": "Mild Swelling or Tenderness - subsides in 1–2 days",
                      "type": "text",
                      "version": 1
                    }
                  ],
                  "direction": null,
                  "format": "",
                  "indent": 0,
                  "type": "paragraph",
                  "version": 1
                }
              ],
              "direction": null,
              "format": "",
              "indent": 0,
              "type": "root",
              "version": 1
            }
          }
        },
        {
          "id": "68e2f0bfbbc80439ae9ac8b1",
          "content": {
            "root": {
              "children": [
                {
                  "children": [
                    {
                      "detail": 0,
                      "format": 0,
                      "mode": "normal",
                      "style": "",
                      "text": "No Major Downtime - normal activities can be resumed immediately",
                      "type": "text",
                      "version": 1
                    }
                  ],
                  "direction": null,
                  "format": "",
                  "indent": 0,
                  "type": "paragraph",
                  "version": 1
                }
              ],
              "direction": null,
              "format": "",
              "indent": 0,
              "type": "root",
              "version": 1
            }
          }
        }
      ],
      "postCareTitle": {
        "root": {
          "children": [
            {
              "children": [
                {
                  "detail": 0,
                  "format": 0,
                  "mode": "normal",
                  "style": "",
                  "text": "Post-Care",
                  "type": "text",
                  "version": 1
                }
              ],
              "direction": null,
              "format": "start",
              "indent": 0,
              "type": "heading",
              "version": 1,
              "tag": "h2"
            }
          ],
          "direction": null,
          "format": "",
          "indent": 0,
          "type": "root",
          "version": 1
        }
      },
      "postCareItems": [
        {
          "id": "68e2f0bf1240271028d7228e",
          "content": {
            "root": {
              "children": [
                {
                  "children": [
                    {
                      "detail": 0,
                      "format": 0,
                      "mode": "normal",
                      "style": "",
                      "text": "Avoid hot showers, saunas, or intense workouts for 24 hours",
                      "type": "text",
                      "version": 1
                    }
                  ],
                  "direction": null,
                  "format": "",
                  "indent": 0,
                  "type": "paragraph",
                  "version": 1
                }
              ],
              "direction": null,
              "format": "",
              "indent": 0,
              "type": "root",
              "version": 1
            }
          }
        },
        {
          "id": "68e2f0bf1b94a4659c230d92",
          "content": {
            "root": {
              "children": [
                {
                  "children": [
                    {
                      "detail": 0,
                      "format": 0,
                      "mode": "normal",
                      "style": "",
                      "text": "Apply sunscreen daily to protect results",
                      "type": "text",
                      "version": 1
                    }
                  ],
                  "direction": null,
                  "format": "",
                  "indent": 0,
                  "type": "paragraph",
                  "version": 1
                }
              ],
              "direction": null,
              "format": "",
              "indent": 0,
              "type": "root",
              "version": 1
            }
          }
        },
        {
          "id": "68e2f0bfec21a26719e3ba0c",
          "content": {
            "root": {
              "children": [
                {
                  "children": [
                    {
                      "detail": 0,
                      "format": 0,
                      "mode": "normal",
                      "style": "",
                      "text": "Use gentle, hydrating skincare for a few days",
                      "type": "text",
                      "version": 1
                    }
                  ],
                  "direction": null,
                  "format": "",
                  "indent": 0,
                  "type": "paragraph",
                  "version": 1
                }
              ],
              "direction": null,
              "format": "",
              "indent": 0,
              "type": "root",
              "version": 1
            }
          }
        },
        {
          "id": "68e2f0bfa115c32c0f98e3b9",
          "content": {
            "root": {
              "children": [
                {
                  "children": [
                    {
                      "detail": 0,
                      "format": 0,
                      "mode": "normal",
                      "style": "",
                      "text": "Stay well-hydrated to support collagen production",
                      "type": "text",
                      "version": 1
                    }
                  ],
                  "direction": null,
                  "format": "",
                  "indent": 0,
                  "type": "paragraph",
                  "version": 1
                }
              ],
              "direction": null,
              "format": "",
              "indent": 0,
              "type": "root",
              "version": 1
            }
          }
        },
        {
          "id": "68e2f0bf82edf17df1144303",
          "content": {
            "root": {
              "children": [
                {
                  "children": [
                    {
                      "detail": 0,
                      "format": 0,
                      "mode": "normal",
                      "style": "",
                      "text": "Follow maintenance sessions as advised",
                      "type": "text",
                      "version": 1
                    }
                  ],
                  "direction": null,
                  "format": "",
                  "indent": 0,
                  "type": "paragraph",
                  "version": 1
                }
              ],
              "direction": null,
              "format": "",
              "indent": 0,
              "type": "root",
              "version": 1
            }
          }
        }
      ],
      "blockType": "post-care"
    },
    {
      "id": "68e2f0bff53466f0b2c61d11",
      "title": {
        "root": {
          "children": [
            {
              "children": [
                {
                  "detail": 0,
                  "format": 0,
                  "mode": "normal",
                  "style": "",
                  "text": "Why The Skin Firm is Pune’s Trusted HIFU Clinic",
                  "type": "text",
                  "version": 1
                }
              ],
              "direction": null,
              "format": "center",
              "indent": 0,
              "type": "heading",
              "version": 1,
              "tag": "h2"
            }
          ],
          "direction": null,
          "format": "",
          "indent": 0,
          "type": "root",
          "version": 1
        }
      },
      "items": [
        {
          "id": "68e2f0bfc88e7fa20169cf73",
          "content": {
            "root": {
              "children": [
                {
                  "children": [
                    {
                      "detail": 0,
                      "format": 0,
                      "mode": "normal",
                      "style": "",
                      "text": "Led by Skin Specialist Dr. Karishma Singh",
                      "type": "text",
                      "version": 1
                    }
                  ],
                  "direction": null,
                  "format": "left",
                  "indent": 0,
                  "type": "paragraph",
                  "version": 1
                }
              ],
              "direction": null,
              "format": "",
              "indent": 0,
              "type": "root",
              "version": 1
            }
          }
        },
        {
          "id": "68e2f0bff25fe922e188aa29",
          "content": {
            "root": {
              "children": [
                {
                  "children": [
                    {
                      "detail": 0,
                      "format": 0,
                      "mode": "normal",
                      "style": "",
                      "text": "Non-surgical alternative to facelift",
                      "type": "text",
                      "version": 1
                    }
                  ],
                  "direction": null,
                  "format": "left",
                  "indent": 0,
                  "type": "paragraph",
                  "version": 1
                }
              ],
              "direction": null,
              "format": "",
              "indent": 0,
              "type": "root",
              "version": 1
            }
          }
        },
        {
          "id": "68e2f0bf89175bf147ec5d3a",
          "content": {
            "root": {
              "children": [
                {
                  "children": [
                    {
                      "detail": 0,
                      "format": 0,
                      "mode": "normal",
                      "style": "",
                      "text": "Personalised treatment mapping for natural results",
                      "type": "text",
                      "version": 1
                    }
                  ],
                  "direction": null,
                  "format": "left",
                  "indent": 0,
                  "type": "paragraph",
                  "version": 1
                }
              ],
              "direction": null,
              "format": "",
              "indent": 0,
              "type": "root",
              "version": 1
            }
          }
        },
        {
          "id": "68e2f0bfa5d122649ecef3b5",
          "content": {
            "root": {
              "children": [
                {
                  "children": [
                    {
                      "detail": 0,
                      "format": 0,
                      "mode": "normal",
                      "style": "",
                      "text": "Advanced HIFU technology with proven safety",
                      "type": "text",
                      "version": 1
                    }
                  ],
                  "direction": null,
                  "format": "left",
                  "indent": 0,
                  "type": "paragraph",
                  "version": 1
                }
              ],
              "direction": null,
              "format": "",
              "indent": 0,
              "type": "root",
              "version": 1
            }
          }
        },
        {
          "id": "68e2f0bf03a46f90af691a70",
          "content": {
            "root": {
              "children": [
                {
                  "children": [
                    {
                      "detail": 0,
                      "format": 0,
                      "mode": "normal",
                      "style": "",
                      "text": "Trusted by patients across Pune for anti-ageing care",
                      "type": "text",
                      "version": 1
                    }
                  ],
                  "direction": null,
                  "format": "left",
                  "indent": 0,
                  "type": "paragraph",
                  "version": 1
                }
              ],
              "direction": null,
              "format": "",
              "indent": 0,
              "type": "root",
              "version": 1
            }
          }
        }
      ],
      "blockType": "bullet-points"
    },
    {
      "id": "68e2f0bffd0524b4f4cae0ac",
      "title": {
        "root": {
          "children": [
            {
              "children": [
                {
                  "detail": 0,
                  "format": 0,
                  "mode": "normal",
                  "style": "",
                  "text": "Patient Testimonials for HIFU in Pune",
                  "type": "text",
                  "version": 1
                }
              ],
              "direction": null,
              "format": "center",
              "indent": 0,
              "type": "heading",
              "version": 1,
              "tag": "h2"
            }
          ],
          "direction": null,
          "format": "",
          "indent": 0,
          "type": "root",
          "version": 1
        }
      },
      "items": [
        {
          "id": "68e2f0bffe527fc5e77106af",
          "content": {
            "root": {
              "children": [
                {
                  "children": [
                    {
                      "detail": 0,
                      "format": 0,
                      "mode": "normal",
                      "style": "",
                      "text": "I had sagging around my jawline. After HIFU at The Skin Firm, my face looks tighter and more youthful without any downtime.",
                      "type": "text",
                      "version": 1
                    }
                  ],
                  "direction": null,
                  "format": "",
                  "indent": 0,
                  "type": "paragraph",
                  "version": 1
                }
              ],
              "direction": null,
              "format": "",
              "indent": 0,
              "type": "root",
              "version": 1
            }
          }
        },
        {
          "id": "68e2f0bfaa774273006366c1",
          "content": {
            "root": {
              "children": [
                {
                  "children": [
                    {
                      "detail": 0,
                      "format": 0,
                      "mode": "normal",
                      "style": "",
                      "text": "It felt like a mini facelift without surgery. My friends noticed the lift, but it still looks natural.",
                      "type": "text",
                      "version": 1
                    }
                  ],
                  "direction": null,
                  "format": "",
                  "indent": 0,
                  "type": "paragraph",
                  "version": 1
                }
              ],
              "direction": null,
              "format": "",
              "indent": 0,
              "type": "root",
              "version": 1
            }
          }
        },
        {
          "id": "68e2f0bfd3decf88c0946130",
          "content": {
            "root": {
              "children": [
                {
                  "children": [
                    {
                      "detail": 0,
                      "format": 0,
                      "mode": "normal",
                      "style": "",
                      "text": "I was nervous about ageing signs, but Dr. Karishma suggested HIFU, and I’m so happy with the results.",
                      "type": "text",
                      "version": 1
                    }
                  ],
                  "direction": null,
                  "format": "",
                  "indent": 0,
                  "type": "paragraph",
                  "version": 1
                }
              ],
              "direction": null,
              "format": "",
              "indent": 0,
              "type": "root",
              "version": 1
            }
          }
        }
      ],
      "blockType": "testimonials"
    },
    {
      "id": "68e2f0bf55a5c58e962d66da",
      "title": {
        "root": {
          "children": [
            {
              "children": [
                {
                  "detail": 0,
                  "format": 0,
                  "mode": "normal",
                  "style": "",
                  "text": "Who Can Benefit from HIFU Treatment?",
                  "type": "text",
                  "version": 1
                }
              ],
              "direction": null,
              "format": "center",
              "indent": 0,
              "type": "heading",
              "version": 1,
              "tag": "h2"
            }
          ],
          "direction": null,
          "format": "",
          "indent": 0,
          "type": "root",
          "version": 1
        }
      },
      "items": [
        {
          "id": "68e2f0bf251d1780585861e0",
          "content": {
            "root": {
              "children": [
                {
                  "children": [
                    {
                      "detail": 0,
                      "format": 0,
                      "mode": "normal",
                      "style": "",
                      "text": "Men & women with mild to moderate sagging skin",
                      "type": "text",
                      "version": 1
                    }
                  ],
                  "direction": null,
                  "format": "",
                  "indent": 0,
                  "type": "paragraph",
                  "version": 1
                }
              ],
              "direction": null,
              "format": "",
              "indent": 0,
              "type": "root",
              "version": 1
            }
          }
        },
        {
          "id": "68e2f0bfbd2dc176e9a58d52",
          "content": {
            "root": {
              "children": [
                {
                  "children": [
                    {
                      "detail": 0,
                      "format": 0,
                      "mode": "normal",
                      "style": "",
                      "text": "Adults in their 30s–50s noticing early ageing signs",
                      "type": "text",
                      "version": 1
                    }
                  ],
                  "direction": null,
                  "format": "",
                  "indent": 0,
                  "type": "paragraph",
                  "version": 1
                }
              ],
              "direction": null,
              "format": "",
              "indent": 0,
              "type": "root",
              "version": 1
            }
          }
        },
        {
          "id": "68e2f0bf2ea9ffc5b746b3fc",
          "content": {
            "root": {
              "children": [
                {
                  "children": [
                    {
                      "detail": 0,
                      "format": 0,
                      "mode": "normal",
                      "style": "",
                      "text": "Those not ready for surgery but seeking visible lift",
                      "type": "text",
                      "version": 1
                    }
                  ],
                  "direction": null,
                  "format": "",
                  "indent": 0,
                  "type": "paragraph",
                  "version": 1
                }
              ],
              "direction": null,
              "format": "",
              "indent": 0,
              "type": "root",
              "version": 1
            }
          }
        },
        {
          "id": "68e2f0bf20388a81d078a966",
          "content": {
            "root": {
              "children": [
                {
                  "children": [
                    {
                      "detail": 0,
                      "format": 0,
                      "mode": "normal",
                      "style": "",
                      "text": "People with double chin or undefined jawline",
                      "type": "text",
                      "version": 1
                    }
                  ],
                  "direction": null,
                  "format": "",
                  "indent": 0,
                  "type": "paragraph",
                  "version": 1
                }
              ],
              "direction": null,
              "format": "",
              "indent": 0,
              "type": "root",
              "version": 1
            }
          }
        },
        {
          "id": "68e2f0bfaa306b3eb382c0f2",
          "content": {
            "root": {
              "children": [
                {
                  "children": [
                    {
                      "detail": 0,
                      "format": 0,
                      "mode": "normal",
                      "style": "",
                      "text": "Anyone wanting non-invasive skin tightening",
                      "type": "text",
                      "version": 1
                    }
                  ],
                  "direction": null,
                  "format": "",
                  "indent": 0,
                  "type": "paragraph",
                  "version": 1
                }
              ],
              "direction": null,
              "format": "",
              "indent": 0,
              "type": "root",
              "version": 1
            }
          }
        }
      ],
      "blockType": "eligibility"
    },
    {
      "id": "68e2f0bf7a94e7df71c1266e",
      "title": {
        "root": {
          "children": [
            {
              "children": [
                {
                  "detail": 0,
                  "format": 0,
                  "mode": "normal",
                  "style": "",
                  "text": "FAQs on HIFU Treatment in Pune",
                  "type": "text",
                  "version": 1
                }
              ],
              "direction": null,
              "format": "center",
              "indent": 0,
              "type": "heading",
              "version": 1,
              "tag": "h2"
            }
          ],
          "direction": null,
          "format": "",
          "indent": 0,
          "type": "root",
          "version": 1
        }
      },
      "items": [
        {
          "id": "68e2f0bf517a3b00150dc9ab",
          "question": "Is HIFU treatment painful?",
          "answer": {
            "root": {
              "children": [
                {
                  "children": [
                    {
                      "detail": 0,
                      "format": 0,
                      "mode": "normal",
                      "style": "",
                      "text": "Most patients feel only mild warmth or tingling. Numbing cream can be applied for extra comfort.",
                      "type": "text",
                      "version": 1
                    }
                  ],
                  "direction": null,
                  "format": "",
                  "indent": 0,
                  "type": "paragraph",
                  "version": 1
                }
              ],
              "direction": null,
              "format": "",
              "indent": 0,
              "type": "root",
              "version": 1
            }
          }
        },
        {
          "id": "68e2f0bfc0d729971aa6beaa",
          "question": "How long does a HIFU session take?",
          "answer": {
            "root": {
              "children": [
                {
                  "children": [
                    {
                      "detail": 0,
                      "format": 0,
                      "mode": "normal",
                      "style": "",
                      "text": "Sessions usually last 45–90 minutes, depending on the area treated.",
                      "type": "text",
                      "version": 1
                    }
                  ],
                  "direction": null,
                  "format": "",
                  "indent": 0,
                  "type": "paragraph",
                  "version": 1
                }
              ],
              "direction": null,
              "format": "",
              "indent": 0,
              "type": "root",
              "version": 1
            }
          }
        },
        {
          "id": "68e2f0bf5970798e3d6bf29e",
          "question": "When will I see results from HIFU?",
          "answer": {
            "root": {
              "children": [
                {
                  "children": [
                    {
                      "detail": 0,
                      "format": 0,
                      "mode": "normal",
                      "style": "",
                      "text": "Some tightening is immediate, but best results develop over 2–3 months as collagen regenerates.",
                      "type": "text",
                      "version": 1
                    }
                  ],
                  "direction": null,
                  "format": "",
                  "indent": 0,
                  "type": "paragraph",
                  "version": 1
                }
              ],
              "direction": null,
              "format": "",
              "indent": 0,
              "type": "root",
              "version": 1
            }
          }
        },
        {
          "id": "68e2f0bf8b3feff120d51f73",
          "question": "How long do HIFU results last?",
          "answer": {
            "root": {
              "children": [
                {
                  "children": [
                    {
                      "detail": 0,
                      "format": 0,
                      "mode": "normal",
                      "style": "",
                      "text": "Results typically last 12–18 months. Maintenance sessions help prolong the effect.",
                      "type": "text",
                      "version": 1
                    }
                  ],
                  "direction": null,
                  "format": "",
                  "indent": 0,
                  "type": "paragraph",
                  "version": 1
                }
              ],
              "direction": null,
              "format": "",
              "indent": 0,
              "type": "root",
              "version": 1
            }
          }
        },
        {
          "id": "68e2f0bf694662e91abbceb5",
          "question": "Is HIFU safe for all skin types?",
          "answer": {
            "root": {
              "children": [
                {
                  "children": [
                    {
                      "detail": 0,
                      "format": 0,
                      "mode": "normal",
                      "style": "",
                      "text": "Yes, HIFU is safe and effective for all skin tones and types.",
                      "type": "text",
                      "version": 1
                    }
                  ],
                  "direction": null,
                  "format": "",
                  "indent": 0,
                  "type": "paragraph",
                  "version": 1
                }
              ],
              "direction": null,
              "format": "",
              "indent": 0,
              "type": "root",
              "version": 1
            }
          }
        },
        {
          "id": "68e2f0bf240590ddc1faf996",
          "question": "Can HIFU replace a surgical facelift?",
          "answer": {
            "root": {
              "children": [
                {
                  "children": [
                    {
                      "detail": 0,
                      "format": 0,
                      "mode": "normal",
                      "style": "",
                      "text": "HIFU provides lifting and tightening but is best for mild to moderate laxity. It’s a non-surgical alternative, not a replacement for severe sagging.",
                      "type": "text",
                      "version": 1
                    }
                  ],
                  "direction": null,
                  "format": "",
                  "indent": 0,
                  "type": "paragraph",
                  "version": 1
                }
              ],
              "direction": null,
              "format": "",
              "indent": 0,
              "type": "root",
              "version": 1
            }
          }
        },
        {
          "id": "68e2f0bf214683db586ca367",
          "question": "Is there any downtime after HIFU?",
          "answer": {
            "root": {
              "children": [
                {
                  "children": [
                    {
                      "detail": 0,
                      "format": 0,
                      "mode": "normal",
                      "style": "",
                      "text": "No major downtime you can return to work or daily life immediately.",
                      "type": "text",
                      "version": 1
                    }
                  ],
                  "direction": null,
                  "format": "",
                  "indent": 0,
                  "type": "paragraph",
                  "version": 1
                }
              ],
              "direction": null,
              "format": "",
              "indent": 0,
              "type": "root",
              "version": 1
            }
          }
        },
        {
          "id": "68e2f0bf4e2beb2877dd8ef7",
          "question": "Can HIFU treat double chin?",
          "answer": {
            "root": {
              "children": [
                {
                  "children": [
                    {
                      "detail": 0,
                      "format": 0,
                      "mode": "normal",
                      "style": "",
                      "text": "Yes, HIFU effectively reduces fat under the chin while tightening skin for a more defined jawline.",
                      "type": "text",
                      "version": 1
                    }
                  ],
                  "direction": null,
                  "format": "",
                  "indent": 0,
                  "type": "paragraph",
                  "version": 1
                }
              ],
              "direction": null,
              "format": "",
              "indent": 0,
              "type": "root",
              "version": 1
            }
          }
        },
        {
          "id": "68e2f0bf3fa6fa11e32cc364",
          "question": "How many sessions of HIFU are needed?",
          "answer": {
            "root": {
              "children": [
                {
                  "children": [
                    {
                      "detail": 0,
                      "format": 0,
                      "mode": "normal",
                      "style": "",
                      "text": "Most patients need only one session, with annual maintenance as recommended.",
                      "type": "text",
                      "version": 1
                    }
                  ],
                  "direction": null,
                  "format": "",
                  "indent": 0,
                  "type": "paragraph",
                  "version": 1
                }
              ],
              "direction": null,
              "format": "",
              "indent": 0,
              "type": "root",
              "version": 1
            }
          }
        },
        {
          "id": "68e2f0bfb58859898f3321b9",
          "question": "Can men get HIFU treatment?",
          "answer": {
            "root": {
              "children": [
                {
                  "children": [
                    {
                      "detail": 0,
                      "format": 0,
                      "mode": "normal",
                      "style": "",
                      "text": "Absolutely many men opt for HIFU for jawline contouring and anti-ageing.",
                      "type": "text",
                      "version": 1
                    }
                  ],
                  "direction": null,
                  "format": "",
                  "indent": 0,
                  "type": "paragraph",
                  "version": 1
                }
              ],
              "direction": null,
              "format": "",
              "indent": 0,
              "type": "root",
              "version": 1
            }
          }
        }
      ],
      "blockType": "faq"
    }
  ]
}