{
  "slug": "stretch-marks-removal",
  "title": "Stretch Marks Removal in Pune",
  "category": "68e307edcf74b65bb67df2c4",
  "updatedAt": "2025-10-05T22:27:11.179Z",
  "createdAt": "2025-10-05T22:27:11.179Z",
  "sections": [
    {
      "id": "68e2f0bfae2c345aa7c674d4",
      "title": {
        "root": {
          "children": [
            {
              "children": [
                {
                  "detail": 0,
                  "format": 0,
                  "mode": "normal",
                  "style": "",
                  "text": "Stretch Marks Removal in Pune - Smooth, Confident Skin with The Skin Firm",
                  "type": "text",
                  "version": 1
                }
              ],
              "direction": null,
              "format": "start",
              "indent": 0,
              "type": "heading",
              "version": 1,
              "tag": "h1"
            }
          ],
          "direction": null,
          "format": "",
          "indent": 0,
          "type": "root",
          "version": 1
        }
      },
      "description": {
        "root": {
          "children": [
            {
              "children": [
                {
                  "detail": 0,
                  "format": 0,
                  "mode": "normal",
                  "style": "",
                  "text": "Safe and advanced ",
                  "type": "text",
                  "version": 1
                },
                {
                  "detail": 0,
                  "format": 1,
                  "mode": "normal",
                  "style": "",
                  "text": "stretch",
                  "type": "text",
                  "version": 1
                },
                {
                  "detail": 0,
                  "format": 0,
                  "mode": "normal",
                  "style": "",
                  "text": " ",
                  "type": "text",
                  "version": 1
                },
                {
                  "detail": 0,
                  "format": 1,
                  "mode": "normal",
                  "style": "",
                  "text": "marks",
                  "type": "text",
                  "version": 1
                },
                {
                  "detail": 0,
                  "format": 0,
                  "mode": "normal",
                  "style": "",
                  "text": " ",
                  "type": "text",
                  "version": 1
                },
                {
                  "detail": 0,
                  "format": 1,
                  "mode": "normal",
                  "style": "",
                  "text": "removal",
                  "type": "text",
                  "version": 1
                },
                {
                  "detail": 0,
                  "format": 0,
                  "mode": "normal",
                  "style": "",
                  "text": " ",
                  "type": "text",
                  "version": 1
                },
                {
                  "detail": 0,
                  "format": 1,
                  "mode": "normal",
                  "style": "",
                  "text": "treatments",
                  "type": "text",
                  "version": 1
                },
                {
                  "detail": 0,
                  "format": 0,
                  "mode": "normal",
                  "style": "",
                  "text": " ",
                  "type": "text",
                  "version": 1
                },
                {
                  "detail": 0,
                  "format": 1,
                  "mode": "normal",
                  "style": "",
                  "text": "in",
                  "type": "text",
                  "version": 1
                },
                {
                  "detail": 0,
                  "format": 0,
                  "mode": "normal",
                  "style": "",
                  "text": " ",
                  "type": "text",
                  "version": 1
                },
                {
                  "detail": 0,
                  "format": 1,
                  "mode": "normal",
                  "style": "",
                  "text": "Pune",
                  "type": "text",
                  "version": 1
                },
                {
                  "detail": 0,
                  "format": 0,
                  "mode": "normal",
                  "style": "",
                  "text": " to fade stubborn marks and improve skin texture, under the care of Skin Specialist ",
                  "type": "text",
                  "version": 1
                },
                {
                  "detail": 0,
                  "format": 1,
                  "mode": "normal",
                  "style": "",
                  "text": "Dr.",
                  "type": "text",
                  "version": 1
                },
                {
                  "detail": 0,
                  "format": 0,
                  "mode": "normal",
                  "style": "",
                  "text": " ",
                  "type": "text",
                  "version": 1
                },
                {
                  "detail": 0,
                  "format": 1,
                  "mode": "normal",
                  "style": "",
                  "text": "Karishma",
                  "type": "text",
                  "version": 1
                },
                {
                  "detail": 0,
                  "format": 0,
                  "mode": "normal",
                  "style": "",
                  "text": " ",
                  "type": "text",
                  "version": 1
                },
                {
                  "detail": 0,
                  "format": 1,
                  "mode": "normal",
                  "style": "",
                  "text": "Singh",
                  "type": "text",
                  "version": 1
                },
                {
                  "detail": 0,
                  "format": 0,
                  "mode": "normal",
                  "style": "",
                  "text": ".",
                  "type": "text",
                  "version": 1
                }
              ],
              "direction": null,
              "format": "start",
              "indent": 0,
              "type": "heading",
              "version": 1,
              "tag": "h4"
            }
          ],
          "direction": null,
          "format": "",
          "indent": 0,
          "type": "root",
          "version": 1
        }
      },
      "blockType": "hero"
    },
    {
      "id": "68e2f0bfa8274ebf8dd96fff",
      "title": {
        "root": {
          "children": [
            {
              "children": [
                {
                  "detail": 0,
                  "format": 0,
                  "mode": "normal",
                  "style": "",
                  "text": "What Are Stretch Marks?",
                  "type": "text",
                  "version": 1
                }
              ],
              "direction": null,
              "format": "center",
              "indent": 0,
              "type": "heading",
              "version": 1,
              "tag": "h2"
            }
          ],
          "direction": null,
          "format": "",
          "indent": 0,
          "type": "root",
          "version": 1
        }
      },
      "description": {
        "root": {
          "children": [
            {
              "children": [
                {
                  "detail": 0,
                  "format": 0,
                  "mode": "normal",
                  "style": "",
                  "text": "Stretch marks, medically known as striae, are long, narrow streaks that develop when the skin stretches too quickly and the collagen and elastin fibers beneath the surface tear. They often start off as red, purple or pink lines and later fade into white or silvery marks.",
                  "type": "text",
                  "version": 1
                }
              ],
              "direction": null,
              "format": "center",
              "indent": 0,
              "type": "paragraph",
              "version": 1
            },
            {
              "children": [
                {
                  "detail": 0,
                  "format": 0,
                  "mode": "normal",
                  "style": "",
                  "text": "They are commonly found on the abdomen, thighs, hips, arms, breasts, and back— appearing after pregnancy, puberty, sudden weight changes, or heavy workouts.",
                  "type": "text",
                  "version": 1
                }
              ],
              "direction": null,
              "format": "center",
              "indent": 0,
              "type": "paragraph",
              "version": 1
            },
            {
              "children": [
                {
                  "detail": 0,
                  "format": 0,
                  "mode": "normal",
                  "style": "",
                  "text": "While harmless, they can affect self-confidence especially when wearing sleeveless clothes, swimwear, or fitted outfits.",
                  "type": "text",
                  "version": 1
                }
              ],
              "direction": null,
              "format": "center",
              "indent": 0,
              "type": "paragraph",
              "version": 1
            },
            {
              "children": [
                {
                  "detail": 0,
                  "format": 0,
                  "mode": "normal",
                  "style": "",
                  "text": "At The Skin Firm, Pune, we offer advanced stretch marks removal treatments that safely reduce their appearance, restore smoother skin, and help you feel confident again.",
                  "type": "text",
                  "version": 1
                }
              ],
              "direction": null,
              "format": "center",
              "indent": 0,
              "type": "paragraph",
              "version": 1
            }
          ],
          "direction": null,
          "format": "",
          "indent": 0,
          "type": "root",
          "version": 1
        }
      },
      "blockType": "info"
    },
    {
      "id": "68e2f0bf62735cc9e8fe7cc8",
      "title": {
        "root": {
          "children": [
            {
              "children": [
                {
                  "detail": 0,
                  "format": 0,
                  "mode": "normal",
                  "style": "",
                  "text": "Signs & Concerns of Stretch Marks",
                  "type": "text",
                  "version": 1
                }
              ],
              "direction": null,
              "format": "center",
              "indent": 0,
              "type": "heading",
              "version": 1,
              "tag": "h2"
            }
          ],
          "direction": null,
          "format": "",
          "indent": 0,
          "type": "root",
          "version": 1
        }
      },
      "items": [
        {
          "id": "68e2f0bffb189b234f6bbc23",
          "content": {
            "root": {
              "children": [
                {
                  "children": [
                    {
                      "detail": 0,
                      "format": 0,
                      "mode": "normal",
                      "style": "",
                      "text": "Red, purple, or pink fresh stretch marks (newer, more active marks)",
                      "type": "text",
                      "version": 1
                    }
                  ],
                  "direction": null,
                  "format": "left",
                  "indent": 0,
                  "type": "paragraph",
                  "version": 1
                }
              ],
              "direction": null,
              "format": "",
              "indent": 0,
              "type": "root",
              "version": 1
            }
          }
        },
        {
          "id": "68e2f0bf956bfc67bf97a85f",
          "content": {
            "root": {
              "children": [
                {
                  "children": [
                    {
                      "detail": 0,
                      "format": 0,
                      "mode": "normal",
                      "style": "",
                      "text": "White or silvery stretch marks (older, settled marks)",
                      "type": "text",
                      "version": 1
                    }
                  ],
                  "direction": null,
                  "format": "left",
                  "indent": 0,
                  "type": "paragraph",
                  "version": 1
                }
              ],
              "direction": null,
              "format": "",
              "indent": 0,
              "type": "root",
              "version": 1
            }
          }
        },
        {
          "id": "68e2f0bf0a37ecfbdea9cd00",
          "content": {
            "root": {
              "children": [
                {
                  "children": [
                    {
                      "detail": 0,
                      "format": 0,
                      "mode": "normal",
                      "style": "",
                      "text": "Indented streaks on the skin, especially abdomen, thighs, and arms",
                      "type": "text",
                      "version": 1
                    }
                  ],
                  "direction": null,
                  "format": "left",
                  "indent": 0,
                  "type": "paragraph",
                  "version": 1
                }
              ],
              "direction": null,
              "format": "",
              "indent": 0,
              "type": "root",
              "version": 1
            }
          }
        },
        {
          "id": "68e2f0bf6e195f80321d96de",
          "content": {
            "root": {
              "children": [
                {
                  "children": [
                    {
                      "detail": 0,
                      "format": 1,
                      "mode": "normal",
                      "style": "",
                      "text": "Post-pregnancy",
                      "type": "text",
                      "version": 1
                    },
                    {
                      "detail": 0,
                      "format": 0,
                      "mode": "normal",
                      "style": "",
                      "text": " ",
                      "type": "text",
                      "version": 1
                    },
                    {
                      "detail": 0,
                      "format": 1,
                      "mode": "normal",
                      "style": "",
                      "text": "stretch",
                      "type": "text",
                      "version": 1
                    },
                    {
                      "detail": 0,
                      "format": 0,
                      "mode": "normal",
                      "style": "",
                      "text": " ",
                      "type": "text",
                      "version": 1
                    },
                    {
                      "detail": 0,
                      "format": 1,
                      "mode": "normal",
                      "style": "",
                      "text": "marks",
                      "type": "text",
                      "version": 1
                    },
                    {
                      "detail": 0,
                      "format": 0,
                      "mode": "normal",
                      "style": "",
                      "text": " (postpartum marks)",
                      "type": "text",
                      "version": 1
                    }
                  ],
                  "direction": null,
                  "format": "left",
                  "indent": 0,
                  "type": "paragraph",
                  "version": 1
                }
              ],
              "direction": null,
              "format": "",
              "indent": 0,
              "type": "root",
              "version": 1
            }
          }
        },
        {
          "id": "68e2f0bffd0306a1364b3a92",
          "content": {
            "root": {
              "children": [
                {
                  "children": [
                    {
                      "detail": 0,
                      "format": 0,
                      "mode": "normal",
                      "style": "",
                      "text": "Marks caused by rapid weight gain or loss",
                      "type": "text",
                      "version": 1
                    }
                  ],
                  "direction": null,
                  "format": "left",
                  "indent": 0,
                  "type": "paragraph",
                  "version": 1
                }
              ],
              "direction": null,
              "format": "",
              "indent": 0,
              "type": "root",
              "version": 1
            }
          }
        },
        {
          "id": "68e2f0bf55f08dca19893674",
          "content": {
            "root": {
              "children": [
                {
                  "children": [
                    {
                      "detail": 0,
                      "format": 0,
                      "mode": "normal",
                      "style": "",
                      "text": "Reduced skin elasticity in affected areas",
                      "type": "text",
                      "version": 1
                    }
                  ],
                  "direction": null,
                  "format": "left",
                  "indent": 0,
                  "type": "paragraph",
                  "version": 1
                }
              ],
              "direction": null,
              "format": "",
              "indent": 0,
              "type": "root",
              "version": 1
            }
          }
        },
        {
          "id": "68e2f0bf7cc1ba0b90e6b5ac",
          "content": {
            "root": {
              "children": [
                {
                  "children": [
                    {
                      "detail": 0,
                      "format": 0,
                      "mode": "normal",
                      "style": "",
                      "text": "Self-consciousness in clothing choices due tvisible marks",
                      "type": "text",
                      "version": 1
                    }
                  ],
                  "direction": null,
                  "format": "left",
                  "indent": 0,
                  "type": "paragraph",
                  "version": 1
                }
              ],
              "direction": null,
              "format": "",
              "indent": 0,
              "type": "root",
              "version": 1
            }
          }
        }
      ],
      "blockType": "bullet-points"
    },
    {
      "id": "68e2f0bf77496dee2a95a6fb",
      "title": {
        "root": {
          "children": [
            {
              "children": [
                {
                  "detail": 0,
                  "format": 0,
                  "mode": "normal",
                  "style": "",
                  "text": "Why Choose Stretch Marks Removal at The Skin Firm?",
                  "type": "text",
                  "version": 1
                }
              ],
              "direction": null,
              "format": "start",
              "indent": 0,
              "type": "heading",
              "version": 1,
              "tag": "h2"
            }
          ],
          "direction": null,
          "format": "",
          "indent": 0,
          "type": "root",
          "version": 1
        }
      },
      "description": {
        "root": {
          "children": [
            {
              "children": [
                {
                  "detail": 0,
                  "format": 0,
                  "mode": "normal",
                  "style": "",
                  "text": "Stretch marks are extremely common, but when they make you feel uncomfortable in your own skin, it’s time to seek treatment. Many people try creams and oils, only to be disappointed with little to no improvement.",
                  "type": "text",
                  "version": 1
                }
              ],
              "direction": null,
              "format": "start",
              "indent": 0,
              "type": "paragraph",
              "version": 1
            },
            {
              "children": [
                {
                  "detail": 0,
                  "format": 0,
                  "mode": "normal",
                  "style": "",
                  "text": "At The Skin Firm, our ",
                  "type": "text",
                  "version": 1
                },
                {
                  "detail": 0,
                  "format": 1,
                  "mode": "normal",
                  "style": "",
                  "text": "dermatologist-supervised",
                  "type": "text",
                  "version": 1
                },
                {
                  "detail": 0,
                  "format": 0,
                  "mode": "normal",
                  "style": "",
                  "text": " ",
                  "type": "text",
                  "version": 1
                },
                {
                  "detail": 0,
                  "format": 1,
                  "mode": "normal",
                  "style": "",
                  "text": "stretch",
                  "type": "text",
                  "version": 1
                },
                {
                  "detail": 0,
                  "format": 0,
                  "mode": "normal",
                  "style": "",
                  "text": " ",
                  "type": "text",
                  "version": 1
                },
                {
                  "detail": 0,
                  "format": 1,
                  "mode": "normal",
                  "style": "",
                  "text": "marks",
                  "type": "text",
                  "version": 1
                },
                {
                  "detail": 0,
                  "format": 0,
                  "mode": "normal",
                  "style": "",
                  "text": " ",
                  "type": "text",
                  "version": 1
                },
                {
                  "detail": 0,
                  "format": 1,
                  "mode": "normal",
                  "style": "",
                  "text": "treatments",
                  "type": "text",
                  "version": 1
                },
                {
                  "detail": 0,
                  "format": 0,
                  "mode": "normal",
                  "style": "",
                  "text": " ",
                  "type": "text",
                  "version": 1
                },
                {
                  "detail": 0,
                  "format": 1,
                  "mode": "normal",
                  "style": "",
                  "text": "in",
                  "type": "text",
                  "version": 1
                },
                {
                  "detail": 0,
                  "format": 0,
                  "mode": "normal",
                  "style": "",
                  "text": " ",
                  "type": "text",
                  "version": 1
                },
                {
                  "detail": 0,
                  "format": 1,
                  "mode": "normal",
                  "style": "",
                  "text": "Pune",
                  "type": "text",
                  "version": 1
                },
                {
                  "detail": 0,
                  "format": 0,
                  "mode": "normal",
                  "style": "",
                  "text": " are:",
                  "type": "text",
                  "version": 1
                }
              ],
              "direction": null,
              "format": "start",
              "indent": 0,
              "type": "paragraph",
              "version": 1
            },
            {
              "children": [
                {
                  "detail": 0,
                  "format": 0,
                  "mode": "normal",
                  "style": "",
                  "text": "> ",
                  "type": "text",
                  "version": 1
                },
                {
                  "detail": 0,
                  "format": 1,
                  "mode": "normal",
                  "style": "",
                  "text": "Dermatologist-supervised",
                  "type": "text",
                  "version": 1
                },
                {
                  "detail": 0,
                  "format": 0,
                  "mode": "normal",
                  "style": "",
                  "text": " – performed under the expert care of Skin Specialist Dr. Karishma Singh",
                  "type": "text",
                  "version": 1
                }
              ],
              "direction": null,
              "format": "start",
              "indent": 0,
              "type": "paragraph",
              "version": 1
            },
            {
              "children": [
                {
                  "detail": 0,
                  "format": 0,
                  "mode": "normal",
                  "style": "",
                  "text": "> ",
                  "type": "text",
                  "version": 1
                },
                {
                  "detail": 0,
                  "format": 1,
                  "mode": "normal",
                  "style": "",
                  "text": "Medical-grade",
                  "type": "text",
                  "version": 1
                },
                {
                  "detail": 0,
                  "format": 0,
                  "mode": "normal",
                  "style": "",
                  "text": " ",
                  "type": "text",
                  "version": 1
                },
                {
                  "detail": 0,
                  "format": 1,
                  "mode": "normal",
                  "style": "",
                  "text": "and",
                  "type": "text",
                  "version": 1
                },
                {
                  "detail": 0,
                  "format": 0,
                  "mode": "normal",
                  "style": "",
                  "text": " ",
                  "type": "text",
                  "version": 1
                },
                {
                  "detail": 0,
                  "format": 1,
                  "mode": "normal",
                  "style": "",
                  "text": "safe",
                  "type": "text",
                  "version": 1
                },
                {
                  "detail": 0,
                  "format": 0,
                  "mode": "normal",
                  "style": "",
                  "text": " – far more effective than over-the-counter products",
                  "type": "text",
                  "version": 1
                }
              ],
              "direction": null,
              "format": "start",
              "indent": 0,
              "type": "paragraph",
              "version": 1
            },
            {
              "children": [
                {
                  "detail": 0,
                  "format": 0,
                  "mode": "normal",
                  "style": "",
                  "text": "> ",
                  "type": "text",
                  "version": 1
                },
                {
                  "detail": 0,
                  "format": 1,
                  "mode": "normal",
                  "style": "",
                  "text": "Customised",
                  "type": "text",
                  "version": 1
                },
                {
                  "detail": 0,
                  "format": 0,
                  "mode": "normal",
                  "style": "",
                  "text": " – tailored to your stretch mark type, skin tone, and body area",
                  "type": "text",
                  "version": 1
                }
              ],
              "direction": null,
              "format": "start",
              "indent": 0,
              "type": "paragraph",
              "version": 1
            },
            {
              "children": [
                {
                  "detail": 0,
                  "format": 0,
                  "mode": "normal",
                  "style": "",
                  "text": "> ",
                  "type": "text",
                  "version": 1
                },
                {
                  "detail": 0,
                  "format": 1,
                  "mode": "normal",
                  "style": "",
                  "text": "Advanced",
                  "type": "text",
                  "version": 1
                },
                {
                  "detail": 0,
                  "format": 0,
                  "mode": "normal",
                  "style": "",
                  "text": " ",
                  "type": "text",
                  "version": 1
                },
                {
                  "detail": 0,
                  "format": 1,
                  "mode": "normal",
                  "style": "",
                  "text": "and",
                  "type": "text",
                  "version": 1
                },
                {
                  "detail": 0,
                  "format": 0,
                  "mode": "normal",
                  "style": "",
                  "text": " ",
                  "type": "text",
                  "version": 1
                },
                {
                  "detail": 0,
                  "format": 1,
                  "mode": "normal",
                  "style": "",
                  "text": "proven",
                  "type": "text",
                  "version": 1
                },
                {
                  "detail": 0,
                  "format": 0,
                  "mode": "normal",
                  "style": "",
                  "text": " – using lasers, microneedling, and PRP for visible results",
                  "type": "text",
                  "version": 1
                }
              ],
              "direction": null,
              "format": "start",
              "indent": 0,
              "type": "paragraph",
              "version": 1
            },
            {
              "children": [
                {
                  "detail": 0,
                  "format": 0,
                  "mode": "normal",
                  "style": "",
                  "text": "We aim not just to treat marks, but to ",
                  "type": "text",
                  "version": 1
                },
                {
                  "detail": 0,
                  "format": 1,
                  "mode": "normal",
                  "style": "",
                  "text": "restore",
                  "type": "text",
                  "version": 1
                },
                {
                  "detail": 0,
                  "format": 0,
                  "mode": "normal",
                  "style": "",
                  "text": " ",
                  "type": "text",
                  "version": 1
                },
                {
                  "detail": 0,
                  "format": 1,
                  "mode": "normal",
                  "style": "",
                  "text": "confidence",
                  "type": "text",
                  "version": 1
                },
                {
                  "detail": 0,
                  "format": 0,
                  "mode": "normal",
                  "style": "",
                  "text": " in your own skin.",
                  "type": "text",
                  "version": 1
                }
              ],
              "direction": null,
              "format": "start",
              "indent": 0,
              "type": "paragraph",
              "version": 1
            }
          ],
          "direction": null,
          "format": "",
          "indent": 0,
          "type": "root",
          "version": 1
        }
      },
      "blockType": "about",
      "image": "68e25252a21844875a4b76ee"
    },
    {
      "id": "68e2f0bf1047449007e25d38",
      "title": {
        "root": {
          "children": [
            {
              "children": [
                {
                  "detail": 0,
                  "format": 0,
                  "mode": "normal",
                  "style": "",
                  "text": "How Our Stretch Removal Marks Treatment Works",
                  "type": "text",
                  "version": 1
                }
              ],
              "direction": null,
              "format": "center",
              "indent": 0,
              "type": "heading",
              "version": 1,
              "tag": "h2"
            }
          ],
          "direction": null,
          "format": "",
          "indent": 0,
          "type": "root",
          "version": 1
        }
      },
      "items": [
        {
          "id": "68e2f0bf4b71237ffcd9113f",
          "title": "Consultation & Skin Analysis",
          "description": {
            "root": {
              "children": [
                {
                  "children": [
                    {
                      "detail": 0,
                      "format": 0,
                      "mode": "normal",
                      "style": "",
                      "text": "We examine the type, depth, and age of your stretch marks to design a suitable plan.",
                      "type": "text",
                      "version": 1
                    }
                  ],
                  "direction": null,
                  "format": "",
                  "indent": 0,
                  "type": "paragraph",
                  "version": 1
                }
              ],
              "direction": null,
              "format": "",
              "indent": 0,
              "type": "root",
              "version": 1
            }
          }
        },
        {
          "id": "68e2f0bff6373cbf07080900",
          "title": "Personalised Treatment Plan",
          "description": {
            "root": {
              "children": [
                {
                  "children": [
                    {
                      "detail": 0,
                      "format": 0,
                      "mode": "normal",
                      "style": "",
                      "text": "Depending on your marks, you may need peels, microneedling, PRP, or laser therapy.",
                      "type": "text",
                      "version": 1
                    }
                  ],
                  "direction": null,
                  "format": "",
                  "indent": 0,
                  "type": "paragraph",
                  "version": 1
                }
              ],
              "direction": null,
              "format": "",
              "indent": 0,
              "type": "root",
              "version": 1
            }
          }
        },
        {
          "id": "68e2f0bfac3ac2a9498be6da",
          "title": "Advanced Procedure",
          "description": {
            "root": {
              "children": [
                {
                  "children": [
                    {
                      "detail": 0,
                      "format": 0,
                      "mode": "normal",
                      "style": "",
                      "text": "Sessions stimulate collagen and elastin production to repair skin and gradually fade marks.",
                      "type": "text",
                      "version": 1
                    }
                  ],
                  "direction": null,
                  "format": "",
                  "indent": 0,
                  "type": "paragraph",
                  "version": 1
                }
              ],
              "direction": null,
              "format": "",
              "indent": 0,
              "type": "root",
              "version": 1
            }
          }
        },
        {
          "id": "68e2f0bf70810e89930bab14",
          "title": "Aftercare & Maintenance",
          "description": {
            "root": {
              "children": [
                {
                  "children": [
                    {
                      "detail": 0,
                      "format": 0,
                      "mode": "normal",
                      "style": "",
                      "text": "You’ll receive skincare guidance and lifestyle tips to maintain results and prevent worsening.",
                      "type": "text",
                      "version": 1
                    }
                  ],
                  "direction": null,
                  "format": "",
                  "indent": 0,
                  "type": "paragraph",
                  "version": 1
                }
              ],
              "direction": null,
              "format": "",
              "indent": 0,
              "type": "root",
              "version": 1
            }
          }
        }
      ],
      "blockType": "process"
    },
    {
      "id": "68e2f0bf6eb1665de35d8d8f",
      "title": {
        "root": {
          "children": [
            {
              "children": [
                {
                  "detail": 0,
                  "format": 0,
                  "mode": "normal",
                  "style": "",
                  "text": "Types of Stretch Marks Removal Treatments We Offer in Pune",
                  "type": "text",
                  "version": 1
                }
              ],
              "direction": null,
              "format": "center",
              "indent": 0,
              "type": "heading",
              "version": 1,
              "tag": "h2"
            }
          ],
          "direction": null,
          "format": "",
          "indent": 0,
          "type": "root",
          "version": 1
        }
      },
      "items": [
        {
          "id": "68e2f0bf6fec6d94b402f3c7",
          "title": "Laser Therapy",
          "description": {
            "root": {
              "children": [
                {
                  "children": [
                    {
                      "detail": 0,
                      "format": 0,
                      "mode": "normal",
                      "style": "",
                      "text": "resurfaces skin, lightens marks, and boosts collagen",
                      "type": "text",
                      "version": 1
                    }
                  ],
                  "direction": null,
                  "format": "",
                  "indent": 0,
                  "type": "paragraph",
                  "version": 1
                }
              ],
              "direction": null,
              "format": "",
              "indent": 0,
              "type": "root",
              "version": 1
            }
          }
        },
        {
          "id": "68e2f0bfad316790a0bce50f",
          "title": "Microneedling (Collagen Induction Therapy)",
          "description": {
            "root": {
              "children": [
                {
                  "children": [
                    {
                      "detail": 0,
                      "format": 0,
                      "mode": "normal",
                      "style": "",
                      "text": "creates microchannels to stimulate healing and reduce scarring",
                      "type": "text",
                      "version": 1
                    }
                  ],
                  "direction": null,
                  "format": "",
                  "indent": 0,
                  "type": "paragraph",
                  "version": 1
                }
              ],
              "direction": null,
              "format": "",
              "indent": 0,
              "type": "root",
              "version": 1
            }
          }
        },
        {
          "id": "68e2f0bf3c30fab7d9f6c0ad",
          "title": "PRP (Platelet-Rich Plasma) Therapy",
          "description": {
            "root": {
              "children": [
                {
                  "children": [
                    {
                      "detail": 0,
                      "format": 0,
                      "mode": "normal",
                      "style": "",
                      "text": "uses growth factors from your blood to repair skin naturally",
                      "type": "text",
                      "version": 1
                    }
                  ],
                  "direction": null,
                  "format": "",
                  "indent": 0,
                  "type": "paragraph",
                  "version": 1
                }
              ],
              "direction": null,
              "format": "",
              "indent": 0,
              "type": "root",
              "version": 1
            }
          }
        },
        {
          "id": "68e2f0bf6adf16c783505bc1",
          "title": "Chemical Peels for stretch marks",
          "description": {
            "root": {
              "children": [
                {
                  "children": [
                    {
                      "detail": 0,
                      "format": 0,
                      "mode": "normal",
                      "style": "",
                      "text": "exfoliate and improve skin tone for newer marks",
                      "type": "text",
                      "version": 1
                    }
                  ],
                  "direction": null,
                  "format": "",
                  "indent": 0,
                  "type": "paragraph",
                  "version": 1
                }
              ],
              "direction": null,
              "format": "",
              "indent": 0,
              "type": "root",
              "version": 1
            }
          }
        },
        {
          "id": "68e2f0bfc0cf82f7b0c361e1",
          "title": "Combination Treatments",
          "description": {
            "root": {
              "children": [
                {
                  "children": [
                    {
                      "detail": 0,
                      "format": 0,
                      "mode": "normal",
                      "style": "",
                      "text": "customised protocols for stubborn or older marks",
                      "type": "text",
                      "version": 1
                    }
                  ],
                  "direction": null,
                  "format": "",
                  "indent": 0,
                  "type": "paragraph",
                  "version": 1
                }
              ],
              "direction": null,
              "format": "",
              "indent": 0,
              "type": "root",
              "version": 1
            }
          }
        },
        {
          "id": "68e2f0bfea9b1031bb21566a",
          "title": "Post Pregnancy Stretch Marks Removal",
          "description": {
            "root": {
              "children": [
                {
                  "children": [
                    {
                      "detail": 0,
                      "format": 0,
                      "mode": "normal",
                      "style": "",
                      "text": "safe, gentle, and effective care for new mothers",
                      "type": "text",
                      "version": 1
                    }
                  ],
                  "direction": null,
                  "format": "",
                  "indent": 0,
                  "type": "paragraph",
                  "version": 1
                }
              ],
              "direction": null,
              "format": "",
              "indent": 0,
              "type": "root",
              "version": 1
            }
          }
        }
      ],
      "blockType": "treatments"
    },
    {
      "id": "68e2f0bff4f3fb2c1f4d7679",
      "title": {
        "root": {
          "children": [
            {
              "children": [
                {
                  "detail": 0,
                  "format": 0,
                  "mode": "normal",
                  "style": "",
                  "text": "Benefits of Stretch Marks Removal at The Skin Firm",
                  "type": "text",
                  "version": 1
                }
              ],
              "direction": null,
              "format": "center",
              "indent": 0,
              "type": "heading",
              "version": 1,
              "tag": "h2"
            }
          ],
          "direction": null,
          "format": "",
          "indent": 0,
          "type": "root",
          "version": 1
        }
      },
      "items": [
        {
          "id": "68e2f0bfe6b51729d444cce9",
          "content": {
            "root": {
              "children": [
                {
                  "children": [
                    {
                      "detail": 0,
                      "format": 0,
                      "mode": "normal",
                      "style": "",
                      "text": "Fades both new and old stretch marks",
                      "type": "text",
                      "version": 1
                    }
                  ],
                  "direction": null,
                  "format": "",
                  "indent": 0,
                  "type": "paragraph",
                  "version": 1
                }
              ],
              "direction": null,
              "format": "",
              "indent": 0,
              "type": "root",
              "version": 1
            }
          }
        },
        {
          "id": "68e2f0bf9510f93c725f352d",
          "content": {
            "root": {
              "children": [
                {
                  "children": [
                    {
                      "detail": 0,
                      "format": 0,
                      "mode": "normal",
                      "style": "",
                      "text": "Improves skin texture and smoothness",
                      "type": "text",
                      "version": 1
                    }
                  ],
                  "direction": null,
                  "format": "",
                  "indent": 0,
                  "type": "paragraph",
                  "version": 1
                }
              ],
              "direction": null,
              "format": "",
              "indent": 0,
              "type": "root",
              "version": 1
            }
          }
        },
        {
          "id": "68e2f0bf784ed05d41d3ace1",
          "content": {
            "root": {
              "children": [
                {
                  "children": [
                    {
                      "detail": 0,
                      "format": 0,
                      "mode": "normal",
                      "style": "",
                      "text": "Boosts collagen and elasticity in the skin",
                      "type": "text",
                      "version": 1
                    }
                  ],
                  "direction": null,
                  "format": "",
                  "indent": 0,
                  "type": "paragraph",
                  "version": 1
                }
              ],
              "direction": null,
              "format": "",
              "indent": 0,
              "type": "root",
              "version": 1
            }
          }
        },
        {
          "id": "68e2f0bf716f5483e7dca0f5",
          "content": {
            "root": {
              "children": [
                {
                  "children": [
                    {
                      "detail": 0,
                      "format": 0,
                      "mode": "normal",
                      "style": "",
                      "text": "Safe for face, arms, thighs, abdomen, and breasts",
                      "type": "text",
                      "version": 1
                    }
                  ],
                  "direction": null,
                  "format": "",
                  "indent": 0,
                  "type": "paragraph",
                  "version": 1
                }
              ],
              "direction": null,
              "format": "",
              "indent": 0,
              "type": "root",
              "version": 1
            }
          }
        },
        {
          "id": "68e2f0bf6aae1b93bf7bd4b0",
          "content": {
            "root": {
              "children": [
                {
                  "children": [
                    {
                      "detail": 0,
                      "format": 0,
                      "mode": "normal",
                      "style": "",
                      "text": "Non-surgical and minimally invasive",
                      "type": "text",
                      "version": 1
                    }
                  ],
                  "direction": null,
                  "format": "",
                  "indent": 0,
                  "type": "paragraph",
                  "version": 1
                }
              ],
              "direction": null,
              "format": "",
              "indent": 0,
              "type": "root",
              "version": 1
            }
          }
        },
        {
          "id": "68e2f0bfaa1e4be070d0f3d1",
          "content": {
            "root": {
              "children": [
                {
                  "children": [
                    {
                      "detail": 0,
                      "format": 0,
                      "mode": "normal",
                      "style": "",
                      "text": "Improves body confidence and comfort in clothing",
                      "type": "text",
                      "version": 1
                    }
                  ],
                  "direction": null,
                  "format": "",
                  "indent": 0,
                  "type": "paragraph",
                  "version": 1
                }
              ],
              "direction": null,
              "format": "",
              "indent": 0,
              "type": "root",
              "version": 1
            }
          }
        },
        {
          "id": "68e2f0bf6e747eeddebf975b",
          "content": {
            "root": {
              "children": [
                {
                  "children": [
                    {
                      "detail": 0,
                      "format": 0,
                      "mode": "normal",
                      "style": "",
                      "text": "Customised care for every skin type and concern",
                      "type": "text",
                      "version": 1
                    }
                  ],
                  "direction": null,
                  "format": "",
                  "indent": 0,
                  "type": "paragraph",
                  "version": 1
                }
              ],
              "direction": null,
              "format": "",
              "indent": 0,
              "type": "root",
              "version": 1
            }
          }
        }
      ],
      "blockType": "benifits"
    },
    {
      "id": "68e2f0bf3199d0b2d476d9ba",
      "title": {
        "root": {
          "children": [
            {
              "children": [
                {
                  "detail": 0,
                  "format": 0,
                  "mode": "normal",
                  "style": "",
                  "text": "Why The Skin Firm Clinic in Pune’s is Trusted for Stretch Marks Removal Treatment",
                  "type": "text",
                  "version": 1
                }
              ],
              "direction": null,
              "format": "center",
              "indent": 0,
              "type": "heading",
              "version": 1,
              "tag": "h2"
            }
          ],
          "direction": null,
          "format": "",
          "indent": 0,
          "type": "root",
          "version": 1
        }
      },
      "items": [
        {
          "id": "68e2f0bff17c92b0ea874f94",
          "content": {
            "root": {
              "children": [
                {
                  "children": [
                    {
                      "detail": 0,
                      "format": 0,
                      "mode": "normal",
                      "style": "",
                      "text": "Led by Skin Specialist Dr. Karishma Singh",
                      "type": "text",
                      "version": 1
                    }
                  ],
                  "direction": null,
                  "format": "left",
                  "indent": 0,
                  "type": "paragraph",
                  "version": 1
                }
              ],
              "direction": null,
              "format": "",
              "indent": 0,
              "type": "root",
              "version": 1
            }
          }
        },
        {
          "id": "68e2f0bfdcac2eff94da14b6",
          "content": {
            "root": {
              "children": [
                {
                  "children": [
                    {
                      "detail": 0,
                      "format": 0,
                      "mode": "normal",
                      "style": "",
                      "text": "Medical-Grade, Advanced Technology - safe and effective treatments",
                      "type": "text",
                      "version": 1
                    }
                  ],
                  "direction": null,
                  "format": "left",
                  "indent": 0,
                  "type": "paragraph",
                  "version": 1
                }
              ],
              "direction": null,
              "format": "",
              "indent": 0,
              "type": "root",
              "version": 1
            }
          }
        },
        {
          "id": "68e2f0bf372bedfa4fc4f6f9",
          "content": {
            "root": {
              "children": [
                {
                  "children": [
                    {
                      "detail": 0,
                      "format": 0,
                      "mode": "normal",
                      "style": "",
                      "text": "Tailored Protocols - every patient gets a customised plan",
                      "type": "text",
                      "version": 1
                    }
                  ],
                  "direction": null,
                  "format": "left",
                  "indent": 0,
                  "type": "paragraph",
                  "version": 1
                }
              ],
              "direction": null,
              "format": "",
              "indent": 0,
              "type": "root",
              "version": 1
            }
          }
        },
        {
          "id": "68e2f0bf28bf59388b627f44",
          "content": {
            "root": {
              "children": [
                {
                  "children": [
                    {
                      "detail": 0,
                      "format": 0,
                      "mode": "normal",
                      "style": "",
                      "text": "Visible Results - with consistent sessions and care",
                      "type": "text",
                      "version": 1
                    }
                  ],
                  "direction": null,
                  "format": "left",
                  "indent": 0,
                  "type": "paragraph",
                  "version": 1
                }
              ],
              "direction": null,
              "format": "",
              "indent": 0,
              "type": "root",
              "version": 1
            }
          }
        },
        {
          "id": "68e2f0bf3cc5cbaf0a65a365",
          "content": {
            "root": {
              "children": [
                {
                  "children": [
                    {
                      "detail": 0,
                      "format": 0,
                      "mode": "normal",
                      "style": "",
                      "text": "Trusted by Patients Across Pune - proven success stories",
                      "type": "text",
                      "version": 1
                    }
                  ],
                  "direction": null,
                  "format": "left",
                  "indent": 0,
                  "type": "paragraph",
                  "version": 1
                }
              ],
              "direction": null,
              "format": "",
              "indent": 0,
              "type": "root",
              "version": 1
            }
          }
        }
      ],
      "blockType": "bullet-points"
    },
    {
      "id": "68e2f0bfedfbab47e6c22016",
      "title": {
        "root": {
          "children": [
            {
              "children": [
                {
                  "detail": 0,
                  "format": 0,
                  "mode": "normal",
                  "style": "",
                  "text": "Patient Testimonials for Stretch Marks Removal in Pune",
                  "type": "text",
                  "version": 1
                }
              ],
              "direction": null,
              "format": "center",
              "indent": 0,
              "type": "heading",
              "version": 1,
              "tag": "h2"
            }
          ],
          "direction": null,
          "format": "",
          "indent": 0,
          "type": "root",
          "version": 1
        }
      },
      "items": [
        {
          "id": "68e2f0bfe0cd3e7092b02628",
          "content": {
            "root": {
              "children": [
                {
                  "children": [
                    {
                      "detail": 0,
                      "format": 0,
                      "mode": "normal",
                      "style": "",
                      "text": "I had stubborn stretch marks after pregnancy that really affected my confidence. After a few sessions at The Skin Firm, they have lightened so much and now I feel comfortable in sleeveless clothes again.",
                      "type": "text",
                      "version": 1
                    }
                  ],
                  "direction": null,
                  "format": "",
                  "indent": 0,
                  "type": "paragraph",
                  "version": 1
                }
              ],
              "direction": null,
              "format": "",
              "indent": 0,
              "type": "root",
              "version": 1
            }
          }
        },
        {
          "id": "68e2f0bf66076efb32dffa0c",
          "content": {
            "root": {
              "children": [
                {
                  "children": [
                    {
                      "detail": 0,
                      "format": 0,
                      "mode": "normal",
                      "style": "",
                      "text": "I tried many creams but nothing worked. Dr. Karishma Singh recommended a combination of microneedling and PRP. The results are amazing. Over time my marks have faded and my skin feels smoother.",
                      "type": "text",
                      "version": 1
                    }
                  ],
                  "direction": null,
                  "format": "",
                  "indent": 0,
                  "type": "paragraph",
                  "version": 1
                }
              ],
              "direction": null,
              "format": "",
              "indent": 0,
              "type": "root",
              "version": 1
            }
          }
        }
      ],
      "blockType": "testimonials"
    },
    {
      "id": "68e2f0bff5f6e59a403d0e3c",
      "title": {
        "root": {
          "children": [
            {
              "children": [
                {
                  "detail": 0,
                  "format": 0,
                  "mode": "normal",
                  "style": "",
                  "text": "Who Can Benefit from Stretch Marks Removal Treatment?",
                  "type": "text",
                  "version": 1
                }
              ],
              "direction": null,
              "format": "center",
              "indent": 0,
              "type": "heading",
              "version": 1,
              "tag": "h2"
            }
          ],
          "direction": null,
          "format": "",
          "indent": 0,
          "type": "root",
          "version": 1
        }
      },
      "items": [
        {
          "id": "68e2f0bf666ba35941fdf4e3",
          "content": {
            "root": {
              "children": [
                {
                  "children": [
                    {
                      "detail": 0,
                      "format": 0,
                      "mode": "normal",
                      "style": "",
                      "text": "Women with post-pregnancy stretch marks",
                      "type": "text",
                      "version": 1
                    }
                  ],
                  "direction": null,
                  "format": "",
                  "indent": 0,
                  "type": "paragraph",
                  "version": 1
                }
              ],
              "direction": null,
              "format": "",
              "indent": 0,
              "type": "root",
              "version": 1
            }
          }
        },
        {
          "id": "68e2f0bf2f003413239a03b5",
          "content": {
            "root": {
              "children": [
                {
                  "children": [
                    {
                      "detail": 0,
                      "format": 0,
                      "mode": "normal",
                      "style": "",
                      "text": "Men & women with marks from gym training or weight fluctuations",
                      "type": "text",
                      "version": 1
                    }
                  ],
                  "direction": null,
                  "format": "",
                  "indent": 0,
                  "type": "paragraph",
                  "version": 1
                }
              ],
              "direction": null,
              "format": "",
              "indent": 0,
              "type": "root",
              "version": 1
            }
          }
        },
        {
          "id": "68e2f0bf7acd38b72f85b8df",
          "content": {
            "root": {
              "children": [
                {
                  "children": [
                    {
                      "detail": 0,
                      "format": 0,
                      "mode": "normal",
                      "style": "",
                      "text": "Teenagers with stretch marks from growth spurts",
                      "type": "text",
                      "version": 1
                    }
                  ],
                  "direction": null,
                  "format": "",
                  "indent": 0,
                  "type": "paragraph",
                  "version": 1
                }
              ],
              "direction": null,
              "format": "",
              "indent": 0,
              "type": "root",
              "version": 1
            }
          }
        },
        {
          "id": "68e2f0bf5d62a16053f550b6",
          "content": {
            "root": {
              "children": [
                {
                  "children": [
                    {
                      "detail": 0,
                      "format": 0,
                      "mode": "normal",
                      "style": "",
                      "text": "Adults with older, stubborn stretch marks",
                      "type": "text",
                      "version": 1
                    }
                  ],
                  "direction": null,
                  "format": "",
                  "indent": 0,
                  "type": "paragraph",
                  "version": 1
                }
              ],
              "direction": null,
              "format": "",
              "indent": 0,
              "type": "root",
              "version": 1
            }
          }
        },
        {
          "id": "68e2f0bfff05b12d406e4c40",
          "content": {
            "root": {
              "children": [
                {
                  "children": [
                    {
                      "detail": 0,
                      "format": 0,
                      "mode": "normal",
                      "style": "",
                      "text": "Anyone wanting smoother, firmer skin",
                      "type": "text",
                      "version": 1
                    }
                  ],
                  "direction": null,
                  "format": "",
                  "indent": 0,
                  "type": "paragraph",
                  "version": 1
                }
              ],
              "direction": null,
              "format": "",
              "indent": 0,
              "type": "root",
              "version": 1
            }
          }
        },
        {
          "id": "68e2f0bf05cefdf16c424b11",
          "content": {
            "root": {
              "children": [
                {
                  "children": [
                    {
                      "detail": 0,
                      "format": 0,
                      "mode": "normal",
                      "style": "",
                      "text": "Safe for all skin tones and types",
                      "type": "text",
                      "version": 1
                    }
                  ],
                  "direction": null,
                  "format": "",
                  "indent": 0,
                  "type": "paragraph",
                  "version": 1
                }
              ],
              "direction": null,
              "format": "",
              "indent": 0,
              "type": "root",
              "version": 1
            }
          }
        }
      ],
      "blockType": "eligibility"
    },
    {
      "id": "68e2f0bf5c96e64e5c40feb5",
      "title": {
        "root": {
          "children": [
            {
              "children": [
                {
                  "detail": 0,
                  "format": 0,
                  "mode": "normal",
                  "style": "",
                  "text": "FAQs on Stretch Marks Removal in Pune",
                  "type": "text",
                  "version": 1
                }
              ],
              "direction": null,
              "format": "center",
              "indent": 0,
              "type": "heading",
              "version": 1,
              "tag": "h2"
            }
          ],
          "direction": null,
          "format": "",
          "indent": 0,
          "type": "root",
          "version": 1
        }
      },
      "items": [
        {
          "id": "68e2f0bf4718773456cc62fa",
          "question": "Can stretch marks be completely removed?",
          "answer": {
            "root": {
              "children": [
                {
                  "children": [
                    {
                      "detail": 0,
                      "format": 0,
                      "mode": "normal",
                      "style": "",
                      "text": "Not fully, but they can be significantly faded and smoothed. Treatments reduce visibility by stimulating collagen repair.",
                      "type": "text",
                      "version": 1
                    }
                  ],
                  "direction": null,
                  "format": "",
                  "indent": 0,
                  "type": "paragraph",
                  "version": 1
                }
              ],
              "direction": null,
              "format": "",
              "indent": 0,
              "type": "root",
              "version": 1
            }
          }
        },
        {
          "id": "68e2f0bf76430b2ead072fad",
          "question": "What is the best treatment for stretch marks?",
          "answer": {
            "root": {
              "children": [
                {
                  "children": [
                    {
                      "detail": 0,
                      "format": 0,
                      "mode": "normal",
                      "style": "",
                      "text": "It depends, lasers and microneedling work best for older marks, while PRP and peels are great for newer ones.",
                      "type": "text",
                      "version": 1
                    }
                  ],
                  "direction": null,
                  "format": "",
                  "indent": 0,
                  "type": "paragraph",
                  "version": 1
                }
              ],
              "direction": null,
              "format": "",
              "indent": 0,
              "type": "root",
              "version": 1
            }
          }
        },
        {
          "id": "68e2f0bfbb6bbc97b52ec3c8",
          "question": "How many sessions will I need?",
          "answer": {
            "root": {
              "children": [
                {
                  "children": [
                    {
                      "detail": 0,
                      "format": 0,
                      "mode": "normal",
                      "style": "",
                      "text": "Usually 4-8 sessions, spaced 3-4 weeks apart, depending on the severity of your marks.",
                      "type": "text",
                      "version": 1
                    }
                  ],
                  "direction": null,
                  "format": "",
                  "indent": 0,
                  "type": "paragraph",
                  "version": 1
                }
              ],
              "direction": null,
              "format": "",
              "indent": 0,
              "type": "root",
              "version": 1
            }
          }
        },
        {
          "id": "68e2f0bf18a78b3ac0cb3ba0",
          "question": "Are the stretch marks removal treatments painful?",
          "answer": {
            "root": {
              "children": [
                {
                  "children": [
                    {
                      "detail": 0,
                      "format": 0,
                      "mode": "normal",
                      "style": "",
                      "text": "Mild discomfort is possible, but numbing creams make the procedure comfortable.",
                      "type": "text",
                      "version": 1
                    }
                  ],
                  "direction": null,
                  "format": "",
                  "indent": 0,
                  "type": "paragraph",
                  "version": 1
                }
              ],
              "direction": null,
              "format": "",
              "indent": 0,
              "type": "root",
              "version": 1
            }
          }
        },
        {
          "id": "68e2f0bfaf6c81f56963cc40",
          "question": "When will I see results of my stretch marks removal treatment?",
          "answer": {
            "root": {
              "children": [
                {
                  "children": [
                    {
                      "detail": 0,
                      "format": 0,
                      "mode": "normal",
                      "style": "",
                      "text": "You’ll notice improvement after 2-3 sessions, with best results after completing the treatment plan.",
                      "type": "text",
                      "version": 1
                    }
                  ],
                  "direction": null,
                  "format": "",
                  "indent": 0,
                  "type": "paragraph",
                  "version": 1
                }
              ],
              "direction": null,
              "format": "",
              "indent": 0,
              "type": "root",
              "version": 1
            }
          }
        },
        {
          "id": "68e2f0bfb3759ef09d5e19bb",
          "question": "Are stretch marks removal results permanent?",
          "answer": {
            "root": {
              "children": [
                {
                  "children": [
                    {
                      "detail": 0,
                      "format": 0,
                      "mode": "normal",
                      "style": "",
                      "text": "The improvement is long-lasting. However, new stretch marks may appear with pregnancy, weight changes or growth.",
                      "type": "text",
                      "version": 1
                    }
                  ],
                  "direction": null,
                  "format": "",
                  "indent": 0,
                  "type": "paragraph",
                  "version": 1
                }
              ],
              "direction": null,
              "format": "",
              "indent": 0,
              "type": "root",
              "version": 1
            }
          }
        },
        {
          "id": "68e2f0bf219a8eaab0ff35f5",
          "question": "Is stretch marks removal treatment safe for all skin tones?",
          "answer": {
            "root": {
              "children": [
                {
                  "children": [
                    {
                      "detail": 0,
                      "format": 0,
                      "mode": "normal",
                      "style": "",
                      "text": "Yes, our treatments are safe and customised for Indian skin tones.",
                      "type": "text",
                      "version": 1
                    }
                  ],
                  "direction": null,
                  "format": "",
                  "indent": 0,
                  "type": "paragraph",
                  "version": 1
                }
              ],
              "direction": null,
              "format": "",
              "indent": 0,
              "type": "root",
              "version": 1
            }
          }
        },
        {
          "id": "68e2f0bf10c7d361b9946b2c",
          "question": "Do home remedies work for stretch marks?",
          "answer": {
            "root": {
              "children": [
                {
                  "children": [
                    {
                      "detail": 0,
                      "format": 0,
                      "mode": "normal",
                      "style": "",
                      "text": "They may moisturise skin but cannot repair deeper damage. Professional treatments are more effective.",
                      "type": "text",
                      "version": 1
                    }
                  ],
                  "direction": null,
                  "format": "",
                  "indent": 0,
                  "type": "paragraph",
                  "version": 1
                }
              ],
              "direction": null,
              "format": "",
              "indent": 0,
              "type": "root",
              "version": 1
            }
          }
        },
        {
          "id": "68e2f0bfe283e7af1d2bae1a",
          "question": "Can men also get stretch mark removal treatments?",
          "answer": {
            "root": {
              "children": [
                {
                  "children": [
                    {
                      "detail": 0,
                      "format": 0,
                      "mode": "normal",
                      "style": "",
                      "text": "Absolutely. Many men develop stretch marks from bodybuilding or weight changes.",
                      "type": "text",
                      "version": 1
                    }
                  ],
                  "direction": null,
                  "format": "",
                  "indent": 0,
                  "type": "paragraph",
                  "version": 1
                }
              ],
              "direction": null,
              "format": "",
              "indent": 0,
              "type": "root",
              "version": 1
            }
          }
        },
        {
          "id": "68e2f0bf4d32efc619dcde54",
          "question": "Is it safe after pregnancy?",
          "answer": {
            "root": {
              "children": [
                {
                  "children": [
                    {
                      "detail": 0,
                      "format": 0,
                      "mode": "normal",
                      "style": "",
                      "text": "Yes, our post-pregnancy protocols are gentle, safe, and effective for new mothers.",
                      "type": "text",
                      "version": 1
                    }
                  ],
                  "direction": null,
                  "format": "",
                  "indent": 0,
                  "type": "paragraph",
                  "version": 1
                }
              ],
              "direction": null,
              "format": "",
              "indent": 0,
              "type": "root",
              "version": 1
            }
          }
        }
      ],
      "blockType": "faq"
    }
  ]
}